shapzero/__init__.py
shapzero/main.py
shapzero/example_data/DNA_sequences.pkl
shapzero/example_data/X_DNA_train.pkl
shapzero/example_data/y_DNA_train.pkl
shapzero/fourier/commands.py
shapzero/fourier/helper.py
shapzero/fourier/helper_signal.py
shapzero/fourier/input_signal.py
shapzero/fourier/input_signal_subsampled.py
shapzero/fourier/models.py
shapzero/fourier/qsft.py
shapzero/fourier/query.py
shapzero/fourier/reconstruct.py
shapzero/fourier/test_helper.py
shapzero/fourier/utils.py
shapzero/shap/shap_explainer.py
shapzero-0.0.4.dist-info/licenses/LICENSE
shapzero-0.0.4.dist-info/METADATA
shapzero-0.0.4.dist-info/WHEEL
shapzero-0.0.4.dist-info/top_level.txt
shapzero-0.0.4.dist-info/RECORD
