Metadata-Version: 2.4
Name: shapzero
Version: 0.0.4
Summary: A Python package for explaining biological sequence models using Shapley values and interactions.
Author-email: Darin Tsui <darint@gatech.edu>
Project-URL: Homepage, https://github.com/amirgroup-codes/shap-zero
Project-URL: Bug Tracker, https://github.com/amirgroup-codes/shap-zero/issues
Keywords: SHAP,explainable AI,bioinformatics,computational biology,machine learning,biological sequence models,interactions
Classifier: Programming Language :: Python :: 3.10
Classifier: Programming Language :: Python :: 3.11
Classifier: Programming Language :: Python :: 3.12
Classifier: License :: OSI Approved :: MIT License
Classifier: Operating System :: OS Independent
Classifier: Topic :: Scientific/Engineering :: Artificial Intelligence
Classifier: Topic :: Scientific/Engineering :: Bio-Informatics
Classifier: Development Status :: 4 - Beta
Requires-Python: >=3.10
License-File: LICENSE
Requires-Dist: numpy
Requires-Dist: pandas
Requires-Dist: matplotlib
Requires-Dist: scikit-learn
Requires-Dist: scipy
Requires-Dist: tqdm
Dynamic: license-file
